MANIFEST.in
README.rst
setup.py
pyduck/__init__.py
pyduck/decorators.py
pyduck/interface.py
pyduck/method.py
pyduck/overloading.py
pyduck/utils.py
pyduck/wrappers.py
pyduck.egg-info/PKG-INFO
pyduck.egg-info/SOURCES.txt
pyduck.egg-info/dependency_links.txt
pyduck.egg-info/top_level.txt